myke/__init__.py
myke/__main__.py
myke/__version__.py
myke/exceptions.py
myke/globals.py
myke/main.py
myke/py.typed
myke/run.py
myke/tasks.py
myke/types.py
myke/utils.py
myke/__pycache__/__init__.cpython-310.pyc
myke/__pycache__/__main__.cpython-310.pyc
myke/__pycache__/__version__.cpython-310.pyc
myke/__pycache__/exceptions.cpython-310.pyc
myke/__pycache__/globals.cpython-310.pyc
myke/__pycache__/main.cpython-310.pyc
myke/__pycache__/run.cpython-310.pyc
myke/__pycache__/tasks.cpython-310.pyc
myke/__pycache__/types.cpython-310.pyc
myke/__pycache__/utils.cpython-310.pyc
myke/io/__init__.py
myke/io/echo.py
myke/io/read.py
myke/io/write.py
myke/io/__pycache__/__init__.cpython-310.pyc
myke/io/__pycache__/echo.cpython-310.pyc
myke/io/__pycache__/read.cpython-310.pyc
myke/io/__pycache__/write.cpython-310.pyc
myke-0.4.1.dist-info/LICENSE
myke-0.4.1.dist-info/METADATA
myke-0.4.1.dist-info/WHEEL
myke-0.4.1.dist-info/entry_points.txt
myke-0.4.1.dist-info/top_level.txt
myke-0.4.1.dist-info/RECORD
