Metadata-Version: 2.1
Name: myke
Version: 0.4.1
Summary: The dynamic Python CLI task runner.
Author-email: Donald Mellenbruch <hello@f2dv.com>
License: GNU GENERAL PUBLIC LICENSE
Project-URL: Homepage, https://www.f2dv.com/r/myke
Project-URL: Repository, https://www.github.com/fresh2dev/myke
Project-URL: Funding, https://www.f2dv.com/fund
Classifier: Programming Language :: Python :: 3
Requires-Python: >=3.8
License-File: LICENSE
Requires-Dist: yapx[extras] ==0.4.0
Requires-Dist: pip >=22.2
Requires-Dist: typing-extensions ; python_version < "3.10"
Provides-Extra: build
Requires-Dist: build ==0.* ; extra == 'build'
Requires-Dist: wheel ==0.* ; extra == 'build'
Requires-Dist: twine ==4.* ; extra == 'build'
Provides-Extra: dev
Requires-Dist: python-lsp-server[rope] ==1.* ; extra == 'dev'
Requires-Dist: pylint ==2.* ; extra == 'dev'
Requires-Dist: pylint-pytest ==1.* ; extra == 'dev'
Requires-Dist: mypy[reports] ==1.* ; extra == 'dev'
Requires-Dist: ruff ==0.* ; extra == 'dev'
Requires-Dist: black[jupyter] ==23.* ; extra == 'dev'
Requires-Dist: isort ==5.* ; extra == 'dev'
Requires-Dist: bump2version ==1.* ; extra == 'dev'
Requires-Dist: pdbpp ; extra == 'dev'
Requires-Dist: ipykernel ; extra == 'dev'
Requires-Dist: ipywidgets ; extra == 'dev'
Requires-Dist: ipython ; extra == 'dev'
Provides-Extra: docs
Requires-Dist: mkdocs ==1.* ; extra == 'docs'
Requires-Dist: mkdocs-material ==9.* ; extra == 'docs'
Requires-Dist: mkdocs-jupyter ==0.24.* ; extra == 'docs'
Requires-Dist: mkdocstrings[python] ==0.20.* ; extra == 'docs'
Requires-Dist: mkdocs-autorefs ==0.* ; extra == 'docs'
Requires-Dist: mkdocs-include-dir-to-nav ==1.* ; extra == 'docs'
Provides-Extra: extras
Requires-Dist: requests ==2.* ; extra == 'extras'
Requires-Dist: pyyaml ; extra == 'extras'
Requires-Dist: python-dotenv ; extra == 'extras'
Requires-Dist: tabulate <1 ; extra == 'extras'
Requires-Dist: ppqueue ==0.4.* ; extra == 'extras'
Requires-Dist: tomli ; (python_version < "3.11") and extra == 'extras'
Provides-Extra: io
Requires-Dist: requests ==2.* ; extra == 'io'
Requires-Dist: pyyaml ; extra == 'io'
Requires-Dist: python-dotenv ; extra == 'io'
Requires-Dist: tabulate <1 ; extra == 'io'
Requires-Dist: ppqueue ==0.4.* ; extra == 'io'
Requires-Dist: tomli ; (python_version < "3.11") and extra == 'io'
Provides-Extra: tests
Requires-Dist: pytest ==7.* ; extra == 'tests'
Requires-Dist: pytest-cov ==4.* ; extra == 'tests'
Requires-Dist: pytest-html ==3.* ; extra == 'tests'
Requires-Dist: pytest-sugar ==0.* ; extra == 'tests'
Requires-Dist: pytest-custom-exit-code ==0.3.* ; extra == 'tests'
Requires-Dist: pylint ==2.* ; extra == 'tests'
Requires-Dist: pylint-pytest ==1.* ; extra == 'tests'
Requires-Dist: packaging ==23.* ; extra == 'tests'
Requires-Dist: mockish ==0.1.* ; extra == 'tests'
Requires-Dist: requests ==2.* ; extra == 'tests'
Requires-Dist: pyyaml ; extra == 'tests'
Requires-Dist: python-dotenv ; extra == 'tests'
Requires-Dist: tabulate <1 ; extra == 'tests'
Requires-Dist: ppqueue ==0.4.* ; extra == 'tests'
Requires-Dist: tomli ; (python_version < "3.11") and extra == 'tests'
